{"options":{"validator":{"$jsonSchema":{"bsonType":"object","required":["member_id","summary_date","total_steps","total_calories","avg_heart_rate"],"properties":{"member_id":{"bsonType":"string"},"summary_date":{"bsonType":"date"},"period_type":{"bsonType":"string","enum":["daily","weekly","monthly"]},"total_steps":{"bsonType":"int","minimum":{"$numberInt":"0"}},"total_calories":{"bsonType":"double","minimum":{"$numberInt":"0"}},"avg_heart_rate":{"bsonType":"double","minimum":{"$numberInt":"40"},"maximum":{"$numberInt":"200"}},"sleep_hours":{"bsonType":"double","minimum":{"$numberInt":"0"},"maximum":{"$numberInt":"24"}},"workout_sessions_count":{"bsonType":"int","minimum":{"$numberInt":"0"}},"achievements":{"bsonType":"array","items":{"bsonType":"string"}},"health_score":{"bsonType":"int","minimum":{"$numberInt":"0"},"maximum":{"$numberInt":"100"}},"active_minutes":{"bsonType":"int","minimum":{"$numberInt":"0"}},"distance_covered":{"bsonType":"double","minimum":{"$numberInt":"0"}},"recovery_score":{"bsonType":"int","minimum":{"$numberInt":"0"},"maximum":{"$numberInt":"100"}}},"additionalProperties":false}},"validationLevel":"strict","validationAction":"error"},"indexes":[{"v":{"$numberInt":"2"},"key":{"_id":{"$numberInt":"1"}},"name":"_id_"}],"uuid":"397c6a18377140cdb73797059be5f1e8","collectionName":"member_activity_summaries","type":"collection"}